{
  "project_info": {
    "project_number": "1088231103903",
    "project_id": "test-30859",
    "storage_bucket": "test-30859.appspot.com"
  },
  "client": [
    {
      "client_info": {
        "mobilesdk_app_id": "1:1088231103903:android:a7e257691a6ba4c0d171aa",
        "android_client_info": {
          "package_name": "com.example.helloworld"
        }
      },
      "oauth_client": [
        {
          "client_id": "1088231103903-3242nbn811rggtqk570odgap0h6ajul8.apps.googleusercontent.com",
          "client_type": 3
        }
      ],
      "api_key": [
        {
          "current_key": "AIzaSyDQgsX8QsE__W5kENRrGyFTMlR-N3xvGMg"
        }
      ],
      "services": {
        "appinvite_service": {
          "other_platform_oauth_client": [
            {
              "client_id": "1088231103903-3242nbn811rggtqk570odgap0h6ajul8.apps.googleusercontent.com",
              "client_type": 3
            }
          ]
        }
      }
    }
  ],
  "configuration_version": "1"
}